{"filename":"db.json","entries":{"BjEMfYFN":{"url":{"raw":"https://meyerweb.com/eric/tools/dencoder/","short":"BjEMfYFN"},"visits":0},"DcFxlYnI":{"url":{"raw":"asdfasdfasdf","short":"DcFxlYnI"},"visits":0},"EjikDWZD":{"url":{"raw":"https%3A%2F%2Fen.wikipedia.org%2Fwiki%2FRurouni_Kenshin%23Anime_series","short":"EjikDWZD"},"visits":0},"EmyaaNwp":{"url":{"raw":"https://meyerweb.com/eric/tools/dencoder/","short":"EmyaaNwp"},"visits":0},"HlJMXgPU":{"url":{"raw":"https://meyerweb.com/eric/tools/dencoder/","short":"HlJMXgPU"},"visits":0},"JfnNoJSZ":{"url":{"raw":"","short":"JfnNoJSZ"},"visits":0},"MsMqJOFT":{"url":{"raw":"https://meyerweb.com/eric/tools/dencoder/","short":"MsMqJOFT"},"visits":0},"OMlGvmYE":{"url":{"raw":"https://meyerweb.com/eric/tools/dencoder/","short":"OMlGvmYE"},"visits":0},"RMzoJQHq":{"url":{"raw":"https://meyerweb.com/eric/tools/dencoder/","short":"RMzoJQHq"},"visits":1},"TqPzmLMy":{"url":{"raw":"https://meyerweb.com/eric/tools/dencoder/","short":"TqPzmLMy"},"visits":0},"UeamEopJ":{"url":{"raw":"","short":"UeamEopJ"},"visits":0},"UzMgdAts":{"url":{"raw":"","short":"UzMgdAts"},"visits":0},"VJxccCST":{"url":{"raw":"https://en.wikipedia.org/wiki/Rurouni_Kenshin#Anime_series","short":"VJxccCST"},"visits":1},"Xewacplg":{"url":{"raw":"https://meyerweb.com/eric/tools/dencoder/","short":"Xewacplg"},"visits":0},"ZCLCHfCa":{"url":{"raw":"https://google.com","short":"ZCLCHfCa"},"visits":0},"dBHIaPGs":{"url":{"raw":"https://google.com","short":"dBHIaPGs"},"visits":0},"dWowtZuj":{"url":{"raw":"https://google.com","short":"dWowtZuj"},"visits":0},"dlDltnxH":{"url":{"raw":"https://meyerweb.com/eric/tools/dencoder/","short":"dlDltnxH"},"visits":0},"eQockucF":{"url":{"raw":"https://en.wikipedia.org/wiki/Rurouni_Kenshin#Anime_series","short":"eQockucF"},"visits":0},"fcZgiUPC":{"url":{"raw":"","short":"fcZgiUPC"},"visits":0},"gGMvIPQq":{"url":{"raw":"https://google.com","short":"gGMvIPQq"},"visits":0},"hvXJNaZn":{"url":{"raw":"","short":"hvXJNaZn"},"visits":0},"iehnYGqv":{"url":{"raw":"https://en.wikipedia.org/wiki/Rurouni_Kenshin%23Anime_series","short":"iehnYGqv"},"visits":0},"sqHUtsCv":{"url":{"raw":"https://meyerweb.com/eric/tools/dencoder/","short":"sqHUtsCv"},"visits":0},"yQTjbANa":{"url":{"raw":"https://chrome.google.com/webstore/detail/advanced-rest-client/hgmloofddffdnphfgcellkdfbfbjeloo/related","short":"yQTjbANa"},"visits":1}}}